bibt/gcp/iam/__init__.py
bibt/gcp/iam/classes.py
bibt/gcp/iam/params.py
bibt/gcp/iam/version.py
bibt_gcp_iam-0.2.0.dist-info/METADATA
bibt_gcp_iam-0.2.0.dist-info/WHEEL
bibt_gcp_iam-0.2.0.dist-info/licenses/LICENSE
bibt_gcp_iam-0.2.0.dist-info/RECORD
