Metadata-Version: 2.4
Name: bibt-gcp-iam
Version: 0.2.0
Summary: Functionality often used by BITS Blue Team (IAM Module).
Project-URL: Bug Tracker, https://github.com/broadinstitute/bibt-gcp-iam/issues
Project-URL: Documentation, https://bibt-gcp-iam.readthedocs.io/en/latest/
Project-URL: Homepage, https://github.com/broadinstitute/bibt-gcp-iam
Author-email: Matthew OBrien <mobrien@broadinstitute.org>
License-File: LICENSE
Classifier: License :: OSI Approved :: MIT License
Classifier: Operating System :: OS Independent
Classifier: Programming Language :: Python :: 3
Classifier: Programming Language :: Python :: 3.9
Classifier: Programming Language :: Python :: 3.10
Classifier: Programming Language :: Python :: 3.11
Classifier: Programming Language :: Python :: 3.12
Classifier: Topic :: Security
Classifier: Topic :: Software Development :: Libraries
Classifier: Topic :: Utilities
Requires-Python: >=3.7
Requires-Dist: google-cloud-iam==2.13.0
